<?xml version="1.0" encoding="UTF-8" standalone="yes"?>
<addon id="script.temperature" name="Room Temperature" version="1.0.0" provider-name="durac">
	<requires>
		<import addon="xbmc.python" version="2.14.0"/>
	</requires>
	<extension point="xbmc.python.script" library="addon.py">
		<provides>executable</provides>
	</extension>
	<extension point="xbmc.addon.metadata">
		<platform>all</platform>
		<summary lang="en">Measures room temperature and humidity</summary>
		<description lang="en">Measures room temperature and humidity with DHT11 on RaspberryPi GPIO 5</description>
		<license>GNU General Public License, v2</license>
		<language></language>
		<source>https://github.com/Schwasrz94/script.temperature</source>
	</extension>
</addon>
